nornir_arista/__init__.py
nornir_arista/connections/__init__.py
nornir_arista/tasks/__init__.py
nornir_arista/tasks/arista_config.py
nornir_arista/tasks/arista_get.py
nornir_arista/tasks/report.py
nornir_arista-0.0.7.dist-info/LICENSE
nornir_arista-0.0.7.dist-info/METADATA
nornir_arista-0.0.7.dist-info/WHEEL
nornir_arista-0.0.7.dist-info/top_level.txt
nornir_arista-0.0.7.dist-info/RECORD
